{
  "book": "deuteronomy",
  "chapter": 16,
  "verses": [
    {
      "v": 1,
      "t": "Observe{H8104} the month{H2320} of Abib{H24}, and keep{H6213} the passover{H6453} Lordunto the {H3068} thy God{H430}: for in the month{H2320} of Abib{H24} Lordthe {H3068} thy God{H430} brought thee forth{H3318} out of Egypt{H4714} by night{H3915}."
    },
    {
      "v": 2,
      "t": "Thou shalt therefore sacrifice{H2076} the passover{H6453} Lordunto the {H3068} thy God{H430}, of the flock{H6629} and the herd{H1241}, in the place{H4725} Lordwhich the {H3068} shall choose{H977} to place{H7931} his name{H8034} there."
    },
    {
      "v": 3,
      "t": "Thou shalt eat{H398} no leavened bread{H2557} with it; seven{H7651} days{H3117} shalt thou eat{H398} unleavened bread{H4682} therewith, even the bread{H3899} of affliction{H6040}; for thou camest forth{H3318} out of the land{H776} of Egypt{H4714} in haste{H2649}: that thou mayest remember{H2142} the day{H3117} when thou camest forth{H3318} out of the land{H776} of Egypt{H4714} all the days{H3117} of thy life{H2416}."
    },
    {
      "v": 4,
      "t": "And there shall be no leavened bread{H7603} seen{H7200} with thee in all thy coast{H1366} seven{H7651} days{H3117}; neither shall there any thing of the flesh{H1320}, which thou sacrificedst{H2076} the first{H7223} day{H3117} at even{H6153}, remain{H3885} all night until the morning{H1242}."
    },
    {
      "v": 5,
      "t": "Thou mayest{H3201} not sacrifice{H2076} the passover{H6453} within any{H259} of thy gates{H8179}, Lordwhich the {H3068} thy God{H430} giveth{H5414} thee:sacrifice: or, kill"
    },
    {
      "v": 6,
      "t": "But at the place{H4725} Lordwhich the {H3068} thy God{H430} shall choose{H977} to place{H7931} his name{H8034} in, there thou shalt sacrifice{H2076} the passover{H6453} at even{H6153}, at the going down{H935} of the sun{H8121}, at the season{H4150} that thou camest forth{H3318} out of Egypt{H4714}."
    },
    {
      "v": 7,
      "t": "And thou shalt roast{H1310} and eat{H398} it in the place{H4725} Lordwhich the {H3068} thy God{H430} shall choose{H977}: and thou shalt turn{H6437} in the morning{H1242}, and go{H1980} unto thy tents{H168}."
    },
    {
      "v": 8,
      "t": "Six{H8337} days{H3117} thou shalt eat{H398} unleavened bread{H4682}: and on the seventh{H7637} day{H3117} shall be a solemn assembly{H6116} Lordto the {H3068} thy God{H430}: thou shalt do{H6213} no work{H4399} therein.solemn…: Heb. restraint"
    },
    {
      "v": 9,
      "t": "Seven{H7651} weeks{H7620} shalt thou number{H5608} unto thee: begin{H2490} to number{H5608} the seven{H7651} weeks{H7620} from such time as thou beginnest{H2490} to put the sickle{H2770} to the corn{H7054}."
    },
    {
      "v": 10,
      "t": "And thou shalt keep{H6213} the feast{H2282} of weeks{H7620} Lordunto the {H3068} thy God{H430} with a tribute{H4530} of a freewill offering{H5071} of thine hand{H3027}, which thou shalt give{H5414} unto the Lord thy God, Lordaccording as the {H3068} thy God{H430} hath blessed{H1288} thee:a tribute: or, sufficiency"
    },
    {
      "v": 11,
      "t": "And thou shalt rejoice{H8055} before{H6440} Lordthe {H3068} thy God{H430}, thou, and thy son{H1121}, and thy daughter{H1323}, and thy manservant{H5650}, and thy maidservant{H519}, and the Levite{H3881} that is within thy gates{H8179}, and the stranger{H1616}, and the fatherless{H3490}, and the widow{H490}, that are among{H7130} you, in the place{H4725} Lordwhich the {H3068} thy God{H430} hath chosen{H977} to place{H7931} his name{H8034} there."
    },
    {
      "v": 12,
      "t": "And thou shalt remember{H2142} that thou wast a bondman{H5650} in Egypt{H4714}: and thou shalt observe{H8104} and do{H6213} these statutes{H2706}."
    },
    {
      "v": 13,
      "t": "Thou shalt observe{H6213} the feast{H2282} of tabernacles{H5521} seven{H7651} days{H3117}, after that thou hast gathered{H622} in thy corn{H1637} and thy wine{H3342}:corn…: Heb. floor, and thy winepress"
    },
    {
      "v": 14,
      "t": "And thou shalt rejoice{H8055} in thy feast{H2282}, thou, and thy son{H1121}, and thy daughter{H1323}, and thy manservant{H5650}, and thy maidservant{H519}, and the Levite{H3881}, the stranger{H1616}, and the fatherless{H3490}, and the widow{H490}, that are within thy gates{H8179}."
    },
    {
      "v": 15,
      "t": "Seven{H7651} days{H3117} shalt thou keep a solemn feast{H2287} Lordunto the {H3068} thy God{H430} in the place{H4725} Lordwhich the {H3068} shall choose{H977}: Lordbecause the {H3068} thy God{H430} shall bless{H1288} thee in all thine increase{H8393}, and in all the works{H4639} of thine hands{H3027}, therefore thou shalt surely rejoice{H8056}."
    },
    {
      "v": 16,
      "t": "Three{H7969} times{H6471} in a year{H8141} shall all thy males{H2138} appear{H7200} before{H6440} Lordthe {H3068} thy God{H430} in the place{H4725} which he shall choose{H977}; in the feast{H2282} of unleavened bread{H4682}, and in the feast{H2282} of weeks{H7620}, and in the feast{H2282} of tabernacles{H5521}: and they shall not appear{H7200} before{H6440} Lordthe {H3068} empty{H7387}:"
    },
    {
      "v": 17,
      "t": "Every man{H376} shall give as he is able{H3027}, according to the blessing{H1293} Lordof the {H3068} thy God{H430} which he hath given{H5414} thee.as…: Heb. according to the gift of his hand"
    },
    {
      "v": 18,
      "t": "Judges{H8199} and officers{H7860} shalt thou make{H5414} thee in all thy gates{H8179}, Lordwhich the {H3068} thy God{H430} giveth{H5414} thee, throughout thy tribes{H7626}: and they shall judge{H8199} the people{H5971} with just{H6664} judgment{H4941}."
    },
    {
      "v": 19,
      "t": "Thou shalt not wrest{H5186} judgment{H4941}; thou shalt not respect{H5234} persons{H6440}, neither take{H3947} a gift{H7810}: for a gift{H7810} doth blind{H5786} the eyes{H5869} of the wise{H2450}, and pervert{H5557} the words{H1697}of the righteous{H6662}.words: or, matters"
    },
    {
      "v": 20,
      "t": "That which is altogether{H6664} just{H6664} shalt thou follow{H7291}, that thou mayest live{H2421}, and inherit{H3423} the land{H776} Lordwhich the {H3068} thy God{H430} giveth{H5414} thee.That which…: Heb. Justice, justice"
    },
    {
      "v": 21,
      "t": "Thou shalt not plant{H5193} thee a grove{H842} of any trees{H6086} near unto{H681} the altar{H4196} Lordof the {H3068} thy God{H430}, which thou shalt make{H6213} thee."
    },
    {
      "v": 22,
      "t": "Neither shalt thou set thee up{H6965} any image{H4676}; Lordwhich the {H3068} thy God{H430} hateth{H8130}.image: or, statue, or, pillar"
    }
  ]
}