{
  "book": "psalms",
  "chapter": 61,
  "verses": [
    {
      "v": 1,
      "t": "Hear my cry, O God; attend unto my prayer."
    },
    {
      "v": 2,
      "t": "From the end of the earth will I cry unto thee, when my heart is overwhelmed: lead me to the rock that is higher than I."
    },
    {
      "v": 3,
      "t": "For thou hast been a shelter for me, and a strong tower from the enemy."
    },
    {
      "v": 4,
      "t": "I will abide in thy tabernacle for ever: I will trust in the covert of thy wings. Selah."
    },
    {
      "v": 5,
      "t": "For thou, O God, hast heard my vows: thou hast given me the heritage of those that fear thy name."
    },
    {
      "v": 6,
      "t": "Thou wilt prolong the king's life: and his years as many generations."
    },
    {
      "v": 7,
      "t": "He shall abide before God for ever: O prepare mercy and truth, which may preserve him."
    },
    {
      "v": 8,
      "t": "So will I sing praise unto thy name for ever, that I may daily perform my vows."
    }
  ]
}